mbtaclient/__init__.py
mbtaclient/mbta_object_store.py
mbtaclient/stop.py
mbtaclient/trip.py
mbtaclient/client/__init__.py
mbtaclient/client/mbta_cache_manager.py
mbtaclient/client/mbta_client.py
mbtaclient/client/mbta_session_manager.py
mbtaclient/handlers/__init__.py
mbtaclient/handlers/base_handler.py
mbtaclient/handlers/departures_handler.py
mbtaclient/handlers/trains_handler.py
mbtaclient/handlers/trips_handler.py
mbtaclient/models/__init__.py
mbtaclient/models/mbta_alert.py
mbtaclient/models/mbta_prediction.py
mbtaclient/models/mbta_route.py
mbtaclient/models/mbta_schedule.py
mbtaclient/models/mbta_stop.py
mbtaclient/models/mbta_trip.py
mbtaclient/models/mbta_vehicle.py
mbtaclient-1.1.31.dist-info/licenses/LICENSE
mbtaclient-1.1.31.dist-info/METADATA
mbtaclient-1.1.31.dist-info/WHEEL
mbtaclient-1.1.31.dist-info/top_level.txt
mbtaclient-1.1.31.dist-info/RECORD
