Metadata-Version: 2.4
Name: MBTAclient
Version: 1.1.31
Summary: A Python client for interacting with the MBTA API
Author-email: Luca Chiabrera <luca.chiabrera@gmail.com>
License: MIT
Project-URL: Homepage, https://github.com/chiabre/MBTAclient
Project-URL: Issues, https://github.com/chiabre/MBTAclient/issues
Classifier: Programming Language :: Python :: 3
Classifier: Programming Language :: Python :: 3.12
Classifier: License :: OSI Approved :: MIT License
Classifier: Operating System :: OS Independent
Requires-Python: >=3.12
License-File: LICENSE
Requires-Dist: aiohttp
Dynamic: license-file
